pyfrp-1.1.12.dist-info/top_level.txt
pyfrp-1.1.12.dist-info/RECORD
pyfrp-1.1.12.dist-info/pbr.json
pyfrp-1.1.12.dist-info/METADATA
pyfrp-1.1.12.dist-info/metadata.json
pyfrp-1.1.12.dist-info/WHEEL
pyfrp-1.1.12.dist-info/DESCRIPTION.rst
pyfrp/PyFRAP_cmdline.py
pyfrp/__init__.py
pyfrp/PyFRAP.py
pyfrp/modules/pyfrp_term_module.py
pyfrp/modules/pyfrp_vtk_module.py
pyfrp/modules/pyfrp_fit_module.py
pyfrp/modules/pyfrp_img_module.py
pyfrp/modules/pyfrp_IO_module.py
pyfrp/modules/pyfrp_stats_module.py
pyfrp/modules/pyfrp_plot_module.py
pyfrp/modules/__init__.py
pyfrp/modules/pyfrp_zstack_module.py
pyfrp/modules/pyfrp_optimization_module.py
pyfrp/modules/pyfrp_sim_module.py
pyfrp/modules/pyfrp_gmsh_IO_module.py
pyfrp/modules/pyfrp_integration_module.py
pyfrp/modules/pyfrp_misc_module.py
pyfrp/modules/pyfrp_gmsh_module.py
pyfrp/modules/pyfrp_geometry_module.py
pyfrp/modules/pyfrp_idx_module.py
pyfrp/modules/pyfrp_openscad_module.py
pyfrp/modules/pyfrp_gmsh_geometry.py
pyfrp/subclasses/pyfrp_analysis.py
pyfrp/subclasses/pyfrp_conf.py
pyfrp/subclasses/pyfrp_molecule.py
pyfrp/subclasses/pyfrp_mesh.py
pyfrp/subclasses/__init__.py
pyfrp/subclasses/pyfrp_geometry.py
pyfrp/subclasses/pyfrp_embryo.py
pyfrp/subclasses/pyfrp_ROI.py
pyfrp/subclasses/pyfrp_fit.py
pyfrp/subclasses/pyfrp_simulation.py
pyfrp/configurations/paths_alex
pyfrp/configurations/paths.cluster
pyfrp/configurations/paths.default
pyfrp/configurations/paths
pyfrp/configurations/macros/lsm2tif.ijm
pyfrp/configurations/macros/czi2tif.ijm
pyfrp/gui/pyfrp_gui_fit_dialogs.py
pyfrp/gui/pyfrp_gui_gmsh_editor.py
pyfrp/gui/pyfrp_gui_geometry_dialogs.py
pyfrp/gui/pyfrp_gui_statistics_dialogs.py
pyfrp/gui/pyfrp_gui_analysis_dialogs.py
pyfrp/gui/pyfrp_gui_simulation_dialogs.py
pyfrp/gui/pyfrp_gui_molecule_dialogs.py
pyfrp/gui/pyfrp_gui_ROI_manager.py
pyfrp/gui/pyfrp_gui_vtk.py
pyfrp/gui/__init__.py
pyfrp/gui/pyfrp_gui_builder.py
pyfrp/gui/pyfrp_gui_basics.py
pyfrp/gui/pyfrp_gui_pinning_dialogs.py
pyfrp/gui/pyfrp_gui_mesh_dialogs.py
pyfrp/gui/pyfrp_gui_embryo_dialogs.py
pyfrp/gui/pyfrp_gui_settings_dialogs.py
pyfrp/gui/pyfrp_app.py
pyfrp/gui/pyfrp_term.py
pyfrp/meshfiles/cone.msh
