Metadata-Version: 2.0
Name: pyfrp
Version: 1.1.12
Summary: PyFRAP: A Python based FRAP analysis tool box
Home-page: https://github.com/alexblaessle/PyFRAP
Author: Alexander Blaessle
Author-email: alexander.blaessle@tuebingen.mpg.de
License: GNU GPL Version 3
Keywords: FRAP,fluorescence,recovery,after,photobleaching,reaction-diffusion,fitting
Platform: ALL
Classifier: Development Status :: 4 - Beta
Classifier: Operating System :: OS Independent
Classifier: Programming Language :: Python :: 2.7
Classifier: Topic :: Scientific/Engineering :: Bio-Informatics
Classifier: Intended Audience :: Science/Research
Classifier: License :: OSI Approved :: GNU General Public License v3 (GPLv3)
Classifier: Programming Language :: Python :: 2.7
Requires-Dist: pyopenssl
Requires-Dist: ndg-httpsclient
Requires-Dist: pyasn1
Requires-Dist: ez-setup
Requires-Dist: numpy
Requires-Dist: scipy
Requires-Dist: matplotlib
Requires-Dist: scikit-image
Requires-Dist: FiPy
Requires-Dist: colorama
Requires-Dist: numpy-stl
Requires-Dist: solidpython
Requires-Dist: wget
Requires-Dist: python-bioformats
